sko_reborn/__init__.py
sko_reborn/fnc.py
sko_reborn/test.py
sko_reborn-0.1.4.dist-info/METADATA
sko_reborn-0.1.4.dist-info/WHEEL
sko_reborn-0.1.4.dist-info/top_level.txt
sko_reborn-0.1.4.dist-info/RECORD
