Metadata-Version: 2.4
Name: sko-reborn
Version: 0.1.4
Summary: Random person generator (fictional data only)
Author: Eren
License: MIT
Project-URL: Homepage, https://pynet.neocities.org
Requires-Python: >=3.8
